README.md
setup.py
mapytex/__init__.py
mapytex.egg-info/PKG-INFO
mapytex.egg-info/SOURCES.txt
mapytex.egg-info/dependency_links.txt
mapytex.egg-info/requires.txt
mapytex.egg-info/top_level.txt
mapytex/calculus/__init__.py
mapytex/calculus/API/__init__.py
mapytex/calculus/API/expression.py
mapytex/calculus/API/renders.py
mapytex/calculus/API/tokens/__init__.py
mapytex/calculus/API/tokens/number.py
mapytex/calculus/API/tokens/polynomial.py
mapytex/calculus/API/tokens/token.py
mapytex/calculus/core/__init__.py
mapytex/calculus/core/arithmetic.py
mapytex/calculus/core/coroutine.py
mapytex/calculus/core/exceptions.py
mapytex/calculus/core/operator.py
mapytex/calculus/core/str2.py
mapytex/calculus/core/tree.py
mapytex/calculus/core/tree_tools.py
mapytex/calculus/core/MO/__init__.py
mapytex/calculus/core/MO/atoms.py
mapytex/calculus/core/MO/exceptions.py
mapytex/calculus/core/MO/fraction.py
mapytex/calculus/core/MO/mo.py
mapytex/calculus/core/MO/monomial.py
mapytex/calculus/core/MO/polynomial.py
mapytex/calculus/core/compute/__init__.py
mapytex/calculus/core/compute/add.py
mapytex/calculus/core/compute/divide.py
mapytex/calculus/core/compute/exceptions.py
mapytex/calculus/core/compute/filters.py
mapytex/calculus/core/compute/minus.py
mapytex/calculus/core/compute/multiply.py
mapytex/calculus/core/compute/power.py
mapytex/calculus/core/random/__init__.py
mapytex/calculus/core/random/int_gene.py
mapytex/calculus/core/random/leaf.py
mapytex/calculus/core/renders/__init__.py
mapytex/calculus/core/renders/tree2tex.py
mapytex/calculus/core/renders/tree2txt.py
mapytex/calculus/core/test/__init__.py
mapytex/calculus/core/test/example_tree.py
mapytex/calculus/core/typing/__init__.py
mapytex/calculus/core/typing/add.py
mapytex/calculus/core/typing/divide.py
mapytex/calculus/core/typing/exceptions.py
mapytex/calculus/core/typing/multiply.py
mapytex/calculus/core/typing/power.py
mapytex/geometry/__init__.py
mapytex/geometry/pythagore.py
mapytex/stat/__init__.py
mapytex/stat/dataset.py
mapytex/stat/number_tools.py
mapytex/stat/random_generator.py
mapytex/stat/weightedDataset.py