Metadata-Version: 1.0
Name: mapytex
Version: 2.1
Summary: Computing like a student
Home-page: http://git.opytex.org/lafrite/Mapytex
Author: Benjamin Bertrand
Author-email: programming@opytex.org
License: UNKNOWN
Platform: UNKNOWN
